searchguard/__init__.py
searchguard/exceptions.py
searchguard/internalusers.py
searchguard/roles.py
searchguard/rolesmapping.py
searchguard/settings.py
searchguard-0.8.1.dist-info/DESCRIPTION.rst
searchguard-0.8.1.dist-info/METADATA
searchguard-0.8.1.dist-info/RECORD
searchguard-0.8.1.dist-info/WHEEL
searchguard-0.8.1.dist-info/metadata.json
searchguard-0.8.1.dist-info/top_level.txt
